func_retry/__init__.py
func_retry-0.1.4.dist-info/METADATA
func_retry-0.1.4.dist-info/WHEEL
func_retry-0.1.4.dist-info/licenses/LICENSE
func_retry-0.1.4.dist-info/RECORD
