Metadata-Version: 2.4
Name: func-retry
Version: 0.1.4
Summary: retry utils
Author-email: fjklqq <fjklqq@gmail.com>
License-File: LICENSE
Requires-Python: >=3.7
